uix/__init__.py
uix/app.py
uix/core/__init__.py
uix/core/flask_server.py
uix/core/htmlgen.py
uix/core/web_server.py
uix-1.0.0.dist-info/LICENSE
uix-1.0.0.dist-info/METADATA
uix-1.0.0.dist-info/WHEEL
uix-1.0.0.dist-info/top_level.txt
uix-1.0.0.dist-info/RECORD
