Metadata-Version: 2.1
Name: uix
Version: 1.0.0
Summary: uix
Author: AIT
Requires-Python: >=3.6
License-File: LICENSE
Requires-Dist: Flask
Requires-Dist: Flask-Cors
Requires-Dist: Flask-SocketIO
